pylibrb-0.1.2.dist-info/RECORD
pylibrb-0.1.2.dist-info/WHEEL
pylibrb-0.1.2.dist-info/entry_points.txt
pylibrb-0.1.2.dist-info/METADATA
pylibrb-0.1.2.dist-info/licenses/LICENSE
pylibrb/__init__.py
pylibrb/pylibrb_ext.cpython-310-darwin.so
pylibrb/py.typed
pylibrb/pylibrb_ext.pyi
