Metadata-Version: 2.1
Name: pylibrb
Version: 0.1.2
Summary: Python bindings for the RubberBand library
Author-Email: Paweł Głomski <pglomski.dev@gmail.com>
License: GPLv2
Classifier: License :: OSI Approved :: GNU General Public License v2 (GPLv2)
Classifier: Intended Audience :: Developers
Classifier: Programming Language :: Python :: 3
Project-URL: Homepage, https://github.com/pawel-glomski/pylibrb
Requires-Python: >=3.8
Requires-Dist: numpy
License-File: LICENSE
